simple_tabby/__init__.py
simple_tabby/stabby.py
stabby-1.0.4.dist-info/METADATA
stabby-1.0.4.dist-info/WHEEL
stabby-1.0.4.dist-info/entry_points.txt
stabby-1.0.4.dist-info/top_level.txt
stabby-1.0.4.dist-info/RECORD
