Metadata-Version: 2.1
Name: stabby
Version: 1.0.4
Summary: A helper for ssh operate in terminal
Home-page: https://github.com/Booooooger/simple_tabby
Author: yombo
Author-email: yombo@qq.com
Keywords: terminal,ssh,tabby like
Classifier: Programming Language :: Python :: 3
Classifier: Operating System :: OS Independent
